poket/__init__.py
tests/__init__.py
tests/test_poket.py
poket-0.0.3.dist-info/LICENSE
poket-0.0.3.dist-info/METADATA
poket-0.0.3.dist-info/WHEEL
poket-0.0.3.dist-info/top_level.txt
poket-0.0.3.dist-info/RECORD
